.gitignore
LICENSE
README.md
setup.py
episodic_memory/__init__.py
episodic_memory/agent.py
episodic_memory/buffer.py
episodic_memory/memory.py
episodic_memory/utils.py
episodic_memory/world.py
episodic_memory.egg-info/PKG-INFO
episodic_memory.egg-info/SOURCES.txt
episodic_memory.egg-info/dependency_links.txt
episodic_memory.egg-info/not-zip-safe
episodic_memory.egg-info/requires.txt
episodic_memory.egg-info/top_level.txt
examples/__init__.py
examples/data.py
examples/data_demo.py
examples/demo_everything.py