Metadata-Version: 1.0
Name: episodic-memory
Version: 0.21
Summary: an episodic memory module
Home-page: https://github.com/qihongl/episodic_memory
Author: Qihong Lu
Author-email: lvqihong1992@gmail.com
License: MIT
Keywords: psychology memory
Platform: UNKNOWN
